calcify/__init__.py
calcify/advanced.py
calcify/basic.py
calcify/geometry.py
calcify/statistics.py
calcify/trignometry.py
calcify/utility.py
calcify-1.0.0.dist-info/licenses/LICENSE
calcify-1.0.0.dist-info/METADATA
calcify-1.0.0.dist-info/WHEEL
calcify-1.0.0.dist-info/top_level.txt
calcify-1.0.0.dist-info/RECORD
