Metadata-Version: 2.4
Name: calcify
Version: 1.0.0
Summary: A small utility math library for Python
Author: Rena Gondaliya
Author-email: mypa2k04@gmail.com
License: MIT
Classifier: Programming Language :: Python :: 3
Classifier: License :: OSI Approved :: MIT License
Classifier: Operating System :: OS Independent
Requires-Python: >=3.6
License-File: LICENSE
Dynamic: author
Dynamic: author-email
Dynamic: classifier
Dynamic: license
Dynamic: license-file
Dynamic: requires-python
Dynamic: summary
